splunk_otel/__init__.py
splunk_otel/cmd/bootstrap.py
splunk_otel/cmd/trace.py
splunk_otel/exporter/zipkin.py
splunk_otel/site/sitecustomize.py
splunk_otel/symbols.py
splunk_otel/tracing.py
splunk_otel/version.py
splunk_otel_python-0.1.1.dist-info/entry_points.txt
splunk_otel_python-0.1.1.dist-info/LICENSE
splunk_otel_python-0.1.1.dist-info/WHEEL
splunk_otel_python-0.1.1.dist-info/METADATA
splunk_otel_python-0.1.1.dist-info/RECORD
